edl_pytorch/__init__.py
edl_pytorch/layer.py
edl_pytorch/loss.py
edl_pytorch-0.0.2.dist-info/LICENCE
edl_pytorch-0.0.2.dist-info/METADATA
edl_pytorch-0.0.2.dist-info/WHEEL
edl_pytorch-0.0.2.dist-info/top_level.txt
edl_pytorch-0.0.2.dist-info/RECORD
